fc_zyj_bigdata.py
fc_zyj_bigdata-1.0.dist-info/METADATA
fc_zyj_bigdata-1.0.dist-info/WHEEL
fc_zyj_bigdata-1.0.dist-info/top_level.txt
fc_zyj_bigdata-1.0.dist-info/RECORD
